LICENSE
MANIFEST.in
README.rst
setup.py
django_counter_cache_field/__init__.py
django_counter_cache_field/counter.py
django_counter_cache_field/fields.py
django_counter_cache_field.egg-info/PKG-INFO
django_counter_cache_field.egg-info/SOURCES.txt
django_counter_cache_field.egg-info/dependency_links.txt
django_counter_cache_field.egg-info/not-zip-safe
django_counter_cache_field.egg-info/requires.txt
django_counter_cache_field.egg-info/top_level.txt
django_counter_cache_field/management/__init__.py
django_counter_cache_field/management/commands/__init__.py
django_counter_cache_field/management/commands/list_counters.py
django_counter_cache_field/management/commands/rebuild_counter.py
docs/Makefile
docs/__init__.py
docs/source/__init__.py
docs/source/conf.py
docs/source/django_model_changes.rst
docs/source/index.rst