Metadata-Version: 2.1
Name: django-counter-cache-field
Version: 0.1.2
Summary: django-counter-cache-field makes it extremely easy to denormalize and keep track of related model counts.
Home-page: http://github.com/enjoy2000/django-counter-cache-field
Author: Hat Dao
Author-email: enjoy3013@gmail.com
License: MIT License
Platform: UNKNOWN
Classifier: Environment :: Web Environment
Classifier: Framework :: Django
Classifier: Intended Audience :: Developers
Classifier: License :: OSI Approved :: MIT License
Classifier: Operating System :: OS Independent
Classifier: Programming Language :: Python
Classifier: Programming Language :: Python :: 3
Classifier: Programming Language :: Python :: 3.6
Classifier: Programming Language :: Python :: 3.7
Classifier: Programming Language :: Python :: 3.8
Classifier: Topic :: Internet :: WWW/HTTP
Classifier: Topic :: Internet :: WWW/HTTP :: Dynamic Content
Provides-Extra: test
